jubtools/__init__.py
jubtools/config.py
jubtools/db.py
jubtools/errors.py
jubtools/httptools.py
jubtools/misctools.py
jubtools/psql.py
jubtools/py.typed
jubtools/sqlt.py
jubtools/systemtools.py
jubtools-1.2.3.dist-info/licenses/LICENSE
jubtools-1.2.3.dist-info/METADATA
jubtools-1.2.3.dist-info/WHEEL
jubtools-1.2.3.dist-info/top_level.txt
jubtools-1.2.3.dist-info/RECORD
