Metadata-Version: 2.4
Name: jubtools
Version: 1.2.3
Summary: Shared tools for my own work
Author-email: Andrew Morcom <jubulani@fastmail.fm>
License:                     GNU GENERAL PUBLIC LICENSE
Project-URL: Repository, https://github.com/Jubulani/jubtools.git
Requires-Python: >=3.10
License-File: LICENSE
Requires-Dist: fastapi
Requires-Dist: toml>=0.10.2
Dynamic: license-file
